README.md
setup.py
chainer_pytorch_migration/__init__.py
chainer_pytorch_migration/allocator.py
chainer_pytorch_migration/datasets.py
chainer_pytorch_migration/links.py
chainer_pytorch_migration/parameter.py
chainer_pytorch_migration/tensor.py
chainer_pytorch_migration.egg-info/PKG-INFO
chainer_pytorch_migration.egg-info/SOURCES.txt
chainer_pytorch_migration.egg-info/dependency_links.txt
chainer_pytorch_migration.egg-info/requires.txt
chainer_pytorch_migration.egg-info/top_level.txt
chainer_pytorch_migration/chainermn/__init__.py
chainer_pytorch_migration/chainermn/optimizers.py
chainer_pytorch_migration/ignite/__init__.py
chainer_pytorch_migration/ignite/collate.py
chainer_pytorch_migration/ignite/extensions.py